pytypest/__init__.py
pytypest/_autouse.py
pytypest/_case.py
pytypest/_fixture.py
pytypest/_fixture_factory.py
pytypest/_hub.py
pytypest/_manager.py
pytypest/_parametrize.py
pytypest/_plugin.py
pytypest/_scope.py
pytypest/_scope_manager.py
pytypest/py.typed
pytypest/experimental/__init__.py
pytypest/experimental/_attr.py
pytypest/experimental/_patcher.py
pytypest/fixtures/__init__.py
pytypest/fixtures/_helpers.py
pytypest/fixtures/_misc.py
pytypest/fixtures/_pytest.py
pytypest-1.0.1.dist-info/LICENSE
pytypest-1.0.1.dist-info/WHEEL
pytypest-1.0.1.dist-info/METADATA
pytypest-1.0.1.dist-info/RECORD
