Metadata-Version: 2.1
Name: pytypest
Version: 1.0.1
Summary: Type-safe and maintainable fixtures and parametrization for pytest.
Keywords: pytest,tests,testing,framework,fixtures
Author-email: Gram <git@orsinium.dev>
Requires-Python: >=3.8
Classifier: Development Status :: 5 - Production/Stable
Classifier: Intended Audience :: Developers
Classifier: License :: OSI Approved :: MIT License
Classifier: Programming Language :: Python
Classifier: Typing :: Typed
Requires-Dist: pytest
Requires-Dist: typing-extensions
Requires-Dist: sphinx ; extra == "docs"
Requires-Dist: myst-parser ; extra == "docs"
Requires-Dist: flake8 ; extra == "lint"
Requires-Dist: isort ; extra == "lint"
Requires-Dist: mypy ; extra == "lint"
Requires-Dist: unify ; extra == "lint"
Requires-Dist: types-requests ; extra == "lint"
Requires-Dist: ruff ; extra == "lint"
Requires-Dist: pytest ; extra == "test"
Requires-Dist: pytest-cov ; extra == "test"
Requires-Dist: requests ; extra == "test"
Project-URL: Source, https://github.com/orsinium-labs/pytypest
Provides-Extra: docs
Provides-Extra: lint
Provides-Extra: test
